ewald-0.1.6.dist-info/METADATA
ewald-0.1.6.dist-info/WHEEL
ewald-0.1.6.dist-info/licenses/PYPI_LICENSE
ewald.libs/libgcc_s-98a1ef30.so.1
ewald/__init__.py
ewald/ewald.abi3.so
ewald-0.1.6.dist-info/RECORD
