Metadata-Version: 2.4
Name: ewald
Version: 0.1.6
Classifier: Intended Audience :: Science/Research
Classifier: Topic :: Scientific/Engineering :: Bio-Informatics
Classifier: Programming Language :: Rust
Classifier: Programming Language :: Python :: Implementation :: CPython
Classifier: Programming Language :: Python :: Implementation :: PyPy
License-File: PYPI_LICENSE
Summary: Ewald SPME force calculations
Keywords: ewald,spme,molecular dynamics,pme,force field
Author-email: David O'Connor <the_alchemist@fastmail.com>
Requires-Python: >=3.10
Project-URL: homepage, https://github.com/David-OConnor/ewald
Project-URL: repository, https://github.com/David-OConnor/ewald
Project-URL: documentation, https://docs.rs/ewald
